nullspace_optimizer/__init__.py
nullspace_optimizer/inout.py
nullspace_optimizer/utils.py
nullspace_optimizer/examples/__init__.py
nullspace_optimizer/examples/run_all.py
nullspace_optimizer/examples/advanced_optimizable_examples/__init__.py
nullspace_optimizer/examples/advanced_optimizable_examples/ex00_bound_constraints.py
nullspace_optimizer/examples/advanced_optimizable_examples/ex01_bound_constraints_sparse.py
nullspace_optimizer/examples/advanced_optimizable_examples/ex01_bound_constraints_sparse_cvxopt.py
nullspace_optimizer/examples/advanced_optimizable_examples/ex02_filter.py
nullspace_optimizer/examples/advanced_optimizable_examples/ex03_symbolic_svanberg.py
nullspace_optimizer/examples/advanced_optimizable_examples/ex04_symbolic_svanberg.py
nullspace_optimizer/examples/advanced_optimizable_examples/ex05_basic_example_symbolic.py
nullspace_optimizer/examples/advanced_optimizable_examples/ex06_provide_gradients.py
nullspace_optimizer/examples/basic_examples/__init__.py
nullspace_optimizer/examples/basic_examples/ex00_basic_problem.py
nullspace_optimizer/examples/basic_examples/ex01_basic_problem_2.py
nullspace_optimizer/examples/basic_examples/ex02_basic_problem_3.py
nullspace_optimizer/examples/basic_examples/ex03_basic_problem_degenerate.py
nullspace_optimizer/examples/basic_examples/ex05_multiple_shootings.py
nullspace_optimizer/examples/basic_examples/ex06_multiple_shootings2.py
nullspace_optimizer/examples/basic_examples/ex07_unconstrained.py
nullspace_optimizer/examples/basic_examples/ex08_degenerate.py
nullspace_optimizer/examples/basic_examples/utils/__init__.py
nullspace_optimizer/examples/basic_examples/utils/draw.py
nullspace_optimizer/examples/basic_examples/utils/draw_pyplot.py
nullspace_optimizer/examples/topopt_examples/__init__.py
nullspace_optimizer/examples/topopt_examples/ex00_compliance.py
nullspace_optimizer/examples/topopt_examples/ex01_compliance_equalized.py
nullspace_optimizer/examples/topopt_examples/ex02_compliance_oc.py
nullspace_optimizer-1.2.6.dist-info/LICENSE
nullspace_optimizer-1.2.6.dist-info/METADATA
nullspace_optimizer-1.2.6.dist-info/WHEEL
nullspace_optimizer-1.2.6.dist-info/top_level.txt
nullspace_optimizer-1.2.6.dist-info/RECORD
