Metadata-Version: 2.1
Name: nullspace-optimizer
Version: 1.2.6
Summary: Null space algorithm for nonlinear constrained optimization
Home-page: https://null-space-optimizer.readthedocs.io/en/latest/
Author: Florian Feppon, Dries Toebat
Author-email: florian.feppon@kuleuven.be
License: GNU GPL version 3
Keywords: nonlinear constrained optimization
Classifier: Programming Language :: Python :: 3
Classifier: License :: OSI Approved :: GNU General Public License v3 (GPLv3)
Classifier: Operating System :: OS Independent
Classifier: Topic :: Scientific/Engineering :: Mathematics
Requires-Python: >=3.9
License-File: LICENSE
Requires-Dist: numpy >=1.26.4
Requires-Dist: scipy >=1.11.4
Requires-Dist: matplotlib >=3.8.3
Requires-Dist: cvxopt >=1.3.2
Requires-Dist: osqp >=0.6.2
Requires-Dist: sympy >=1.12
Requires-Dist: qpalm >=1.2.2
Requires-Dist: colored >=1.4.4
